corrai/__init__.py
corrai/cluster.py
corrai/fmu.py
corrai/optimize.py
corrai/sampling.py
corrai/sensitivity.py
corrai/surrogate.py
corrai/base/__init__.py
corrai/base/math.py
corrai/base/metrics.py
corrai/base/model.py
corrai/base/parameter.py
corrai/base/simulate.py
corrai/base/utils.py
corrai-1.1.0.dist-info/licenses/LICENSE.md
corrai-1.1.0.dist-info/WHEEL
corrai-1.1.0.dist-info/METADATA
corrai-1.1.0.dist-info/RECORD
