Metadata-Version: 2.4
Name: corrai
Version: 1.1.0
Summary: Model sampling, sensitivity analisys, uncertainty, surrogates
Author-email: Nobatek/INEF4 <bdurandestebe@nobatek.inef4.com>
Requires-Python: >=3.10
License-Expression: BSD-3-Clause
Classifier: Development Status :: 4 - Beta
Classifier: Intended Audience :: Developers
Classifier: Topic :: Scientific/Engineering
Classifier: Programming Language :: Python :: 3.10
Classifier: Programming Language :: Python :: 3.11
Classifier: Programming Language :: Python :: 3.12
Classifier: Programming Language :: Python :: 3.13
License-File: LICENSE.md
Requires-Dist: numpy>=1.22.4,<2.0
Requires-Dist: pandas>=2.1.0,<3.0
Requires-Dist: scipy>=1.9.1,<2.0
Requires-Dist: scikit-learn>=1.2.2,<2.0
Requires-Dist: pymoo>=0.6.0.1
Requires-Dist: salib>=1.4.7
Requires-Dist: fmpy>=0.3.6
Requires-Dist: matplotlib>=3.5.1
Requires-Dist: plotly>=5.3.1
Requires-Dist: fastprogress>=1.0.3
Project-URL: Homepage, https://github.com/BuildingEnergySimulationTools/corrai
